{
  "url": "reclaimtaxcredits.com",
  "name": "FICA Tax Credits & Refunds",
  "@type": "Organization",
  "slogan": "Your Tips Are a Recoverable Asset.",
  "@context": "https://schema.org",
  "telephone": "(213) 537-5613",
  "areaServed": [
    {
      "name": "San Diego",
      "@type": "City"
    },
    {
      "name": "Los Angeles",
      "@type": "City"
    },
    {
      "name": "San Jose",
      "@type": "City"
    },
    {
      "name": "San Francisco",
      "@type": "City"
    },
    {
      "name": "Sacramento",
      "@type": "City"
    },
    {
      "name": "Salt Lake City",
      "@type": "City"
    },
    {
      "name": "Ogden",
      "@type": "City"
    },
    {
      "name": "Reno",
      "@type": "City"
    },
    {
      "name": "Las Vegas",
      "@type": "City"
    },
    {
      "name": "Phoenix",
      "@type": "City"
    },
    {
      "name": "Denver",
      "@type": "City"
    },
    {
      "name": "Colorado Springs",
      "@type": "City"
    },
    {
      "name": "Minneapolis",
      "@type": "City"
    },
    {
      "name": "St Paul",
      "@type": "City"
    },
    {
      "name": "Chicago",
      "@type": "City"
    },
    {
      "name": "Nashville",
      "@type": "City"
    },
    {
      "name": "Atlanta",
      "@type": "City"
    },
    {
      "name": "Dallas Ft Worth",
      "@type": "City"
    },
    {
      "name": "Austin",
      "@type": "City"
    },
    {
      "name": "San Antonio",
      "@type": "City"
    },
    {
      "name": "Houston",
      "@type": "City"
    },
    {
      "name": "New York",
      "@type": "City"
    },
    {
      "name": "Buffalo",
      "@type": "City"
    },
    {
      "name": "Detroit",
      "@type": "City"
    },
    {
      "name": "Philadelphia",
      "@type": "City"
    },
    {
      "name": "New York City",
      "@type": "City"
    },
    {
      "name": "Boston",
      "@type": "City"
    },
    {
      "name": "Miami",
      "@type": "City"
    },
    {
      "name": "Jacksonville",
      "@type": "City"
    },
    {
      "name": "Oklahoma City",
      "@type": "City"
    },
    {
      "name": "Scottsdale",
      "@type": "City"
    }
  ],
  "description": "A compliance-first tax consultancy service helping restaurants, bars and nightclubs CPA/accountants learn how to gain tax credits and refunds. We specialize in leveraging federal programs to capture tax credits and maximize FICA tax refunds for the past 3 years to increase profitability for businesses. Get exact numbers the IRS owes you at no charge. No fees unless you receive a refund, only then do we charge a small percentage of that refund/credit you receive.",
  "foundingDate": "1993",
  "hasOfferCatalog": {
    "name": "FICA Tax Credits & Refunds Services",
    "@type": "OfferCatalog",
    "itemListElement": [
      {
        "@type": "Offer",
        "itemOffered": {
          "name": "FICA Tip Credit Recovery",
          "@type": "Service"
        }
      },
      {
        "@type": "Offer",
        "itemOffered": {
          "name": "3-Year Retroactive FICA Tax Claims",
          "@type": "Service"
        }
      },
      {
        "@type": "Offer",
        "itemOffered": {
          "name": "Audit Defense for FICA Tax Credits",
          "@type": "Service"
        }
      },
      {
        "@type": "Offer",
        "itemOffered": {
          "name": "Amended FICA Tax Return Filing for Refunds",
          "@type": "Service"
        }
      },
      {
        "@type": "Offer",
        "itemOffered": {
          "name": "Payroll FICA Tax Credit Calculation",
          "@type": "Service"
        }
      },
      {
        "@type": "Offer",
        "itemOffered": {
          "name": "20-Year FICA Tax Credit Carry-Forward Management",
          "@type": "Service"
        }
      },
      {
        "@type": "Offer",
        "itemOffered": {
          "name": "FICA tip credit",
          "@type": "Service"
        }
      },
      {
        "@type": "Offer",
        "itemOffered": {
          "name": "nightclub tip credit refund",
          "@type": "Service"
        }
      },
      {
        "@type": "Offer",
        "itemOffered": {
          "name": "bar tip credit refund",
          "@type": "Service"
        }
      },
      {
        "@type": "Offer",
        "itemOffered": {
          "name": "restaurant tax credit refunds",
          "@type": "Service"
        }
      },
      {
        "@type": "Offer",
        "itemOffered": {
          "name": "FICA refund",
          "@type": "Service"
        }
      },
      {
        "@type": "Offer",
        "itemOffered": {
          "name": "FICA tip credit refunds",
          "@type": "Service"
        }
      },
      {
        "@type": "Offer",
        "itemOffered": {
          "name": "restaurant payroll tax FICA refunds",
          "@type": "Service"
        }
      },
      {
        "@type": "Offer",
        "itemOffered": {
          "name": "what is FICA tip credit",
          "@type": "Service"
        }
      },
      {
        "@type": "Offer",
        "itemOffered": {
          "name": "what is FICA tip tax credit",
          "@type": "Service"
        }
      },
      {
        "@type": "Offer",
        "itemOffered": {
          "name": "how to claim FICA tip credit",
          "@type": "Service"
        }
      },
      {
        "@type": "Offer",
        "itemOffered": {
          "name": "how does FICA tip credit work",
          "@type": "Service"
        }
      },
      {
        "@type": "Offer",
        "itemOffered": {
          "name": "how to calculate FICA tip credit for employers",
          "@type": "Service"
        }
      },
      {
        "@type": "Offer",
        "itemOffered": {
          "name": "how is FICA tip credit calculated",
          "@type": "Service"
        }
      },
      {
        "@type": "Offer",
        "itemOffered": {
          "name": "FICA tip credit for restaurants",
          "@type": "Service"
        }
      },
      {
        "@type": "Offer",
        "itemOffered": {
          "name": "FICA tip credit for employers",
          "@type": "Service"
        }
      },
      {
        "@type": "Offer",
        "itemOffered": {
          "name": "FICA tip credit program",
          "@type": "Service"
        }
      },
      {
        "@type": "Offer",
        "itemOffered": {
          "name": "FICA tip credit IRS",
          "@type": "Service"
        }
      },
      {
        "@type": "Offer",
        "itemOffered": {
          "name": "Retroactive Tax Claims (up to 3 years)",
          "@type": "Service"
        }
      },
      {
        "@type": "Offer",
        "itemOffered": {
          "name": "Audit Defense for Credit Claims",
          "@type": "Service"
        }
      },
      {
        "@type": "Offer",
        "itemOffered": {
          "name": "Amended Return Filing",
          "@type": "Service"
        }
      },
      {
        "@type": "Offer",
        "itemOffered": {
          "name": "20-Year Carry-Forward Tax Credit Management",
          "@type": "Service"
        }
      }
    ]
  }
}